sim/__init__.py
sim/base.py
sim/bm25.py
sim/lsh.py
sim/sif_usif.py
sim/tf_idf.py
sim/pytorch/__init__.py
sim/pytorch/common.py
sim/pytorch/layers.py
sim/pytorch/modeling_albert.py
sim/pytorch/modeling_bert.py
sim/pytorch/modeling_char_cnn.py
sim/pytorch/modeling_colbert.py
sim/pytorch/modeling_deberta.py
sim/pytorch/modeling_fasttext.py
sim/pytorch/modeling_nezha.py
sim/pytorch/modeling_poly_encoder.py
sim/pytorch/modeling_re2.py
sim/pytorch/modeling_siamese_rnn.py
sim/pytorch/modeling_text_cnn.py
sim/pytorch/modeling_text_vdcnn.py
sim/pytorch/pipeline.py
sim/tensorflow/__init__.py
sim/tensorflow/common.py
sim/tensorflow/layers.py
sim/tensorflow/modeling_albert.py
sim/tensorflow/modeling_bert.py
sim/tensorflow/modeling_char_cnn.py
sim/tensorflow/modeling_colbert.py
sim/tensorflow/modeling_fasttext.py
sim/tensorflow/modeling_nezha.py
sim/tensorflow/modeling_poly_encoder.py
sim/tensorflow/modeling_re2.py
sim/tensorflow/modeling_siamese_rnn.py
sim/tensorflow/modeling_text_cnn.py
sim/tensorflow/modeling_text_vdcnn.py
sim/tensorflow/optimizers.py
sim/tensorflow/pipeline.py
sim/tools/__init__.py
sim/tools/pipeline.py
sim/tools/settings.py
sim/tools/similarity.py
sim/tools/tokenizer.py
sim/tools/tools.py
sim/tools/word2vec.py
text_sim-1.0.7.dist-info/LICENSE
text_sim-1.0.7.dist-info/METADATA
text_sim-1.0.7.dist-info/WHEEL
text_sim-1.0.7.dist-info/top_level.txt
text_sim-1.0.7.dist-info/RECORD
