Metadata-Version: 2.1
Name: text-sim
Version: 1.0.7
Summary: Chinese text similarity calculation package of Tensorflow/Pytorch
Home-page: https://github.com/DengBoCong/text-similarity
Author: DengBoCong
Author-email: bocongdeng@gmail.com
License: MIT License
Project-URL: Bug Reports, https://github.com/DengBoCong/text-similarity/issues
Project-URL: Funding, https://pypi.org/project/text-sim/
Project-URL: Source, https://github.com/DengBoCong/text-similarity
Keywords: similarity,tensorflow,pytorch,classification
Platform: UNKNOWN
Classifier: Programming Language :: Python :: 3
Classifier: Programming Language :: Python :: 3.7
Classifier: Programming Language :: Python :: 3.8
Classifier: License :: OSI Approved :: MIT License
Classifier: Operating System :: OS Independent
License-File: LICENSE
Requires-Dist: jieba (==0.42.1)
Requires-Dist: numpy (==1.19.5)
Requires-Dist: tensorflow (==2.6.0)
Requires-Dist: torch (==1.10.0)
Requires-Dist: scikit-learn (==0.24.2)
Requires-Dist: transformers (==4.12.5)
Requires-Dist: tokenizers (==0.10.3)
Requires-Dist: packaging (==21.3)
Requires-Dist: tqdm (==4.62.3)
Requires-Dist: pandas (==1.3.4)
Requires-Dist: networkx (==2.6.3)
Requires-Dist: nltk (==3.6.5)
Requires-Dist: gensim (==4.1.2)
Requires-Dist: sentencepiece (==0.1.96)
